chai/__init__.py
chai/__main__.py
chai_cli-0.3.0.dist-info/LICENSE
chai_cli-0.3.0.dist-info/METADATA
chai_cli-0.3.0.dist-info/WHEEL
chai_cli-0.3.0.dist-info/entry_points.txt
chai_cli-0.3.0.dist-info/top_level.txt
chai_cli-0.3.0.dist-info/RECORD
