Metadata-Version: 2.1
Name: chai-cli
Version: 0.3.0
Summary: AI in your CLI.
Author: Ritik Sahni
Author-email: ritiksahni0203@gmail.com
Keywords: ai,openai,cli
License-File: LICENSE
Requires-Dist: openai
Requires-Dist: argparse
Requires-Dist: pyperclip
